<TextureAtlas imagePath="sprites.png">
    <SubTexture name="dead1.png" x="0" y="456" width="56" height="51"/>
    <SubTexture name="dead10.png" x="58" y="456" width="56" height="51"/>
    <SubTexture name="dead2.png" x="290" y="444" width="56" height="51"/>
    <SubTexture name="dead3.png" x="290" y="391" width="56" height="51"/>
    <SubTexture name="dead4.png" x="290" y="338" width="56" height="51"/>
    <SubTexture name="dead5.png" x="290" y="285" width="56" height="51"/>
    <SubTexture name="dead6.png" x="232" y="456" width="56" height="51"/>
    <SubTexture name="dead7.png" x="174" y="456" width="56" height="51"/>
    <SubTexture name="dead8.png" x="116" y="456" width="56" height="51"/>
    <SubTexture name="dead9.png" x="58" y="456" width="56" height="51"/>
    <SubTexture name="idle1.png" x="290" y="228" width="56" height="55"/>
    <SubTexture name="idle10.png" x="232" y="171" width="56" height="55"/>
    <SubTexture name="idle2.png" x="290" y="171" width="56" height="55"/>
    <SubTexture name="idle3.png" x="290" y="114" width="56" height="55"/>
    <SubTexture name="idle4.png" x="290" y="57" width="56" height="55"/>
    <SubTexture name="idle5.png" x="290" y="0" width="56" height="55"/>
    <SubTexture name="idle6.png" x="232" y="399" width="56" height="55"/>
    <SubTexture name="idle7.png" x="232" y="342" width="56" height="55"/>
    <SubTexture name="idle8.png" x="232" y="285" width="56" height="55"/>
    <SubTexture name="idle9.png" x="232" y="228" width="56" height="55"/>
    <SubTexture name="jump1.png" x="174" y="285" width="56" height="55"/>
    <SubTexture name="jump10.png" x="116" y="285" width="56" height="55"/>
    <SubTexture name="jump2.png" x="174" y="228" width="56" height="55"/>
    <SubTexture name="jump3.png" x="174" y="171" width="56" height="55"/>
    <SubTexture name="jump4.png" x="348" y="0" width="56" height="55"/>
    <SubTexture name="jump5.png" x="174" y="114" width="56" height="55"/>
    <SubTexture name="jump6.png" x="174" y="57" width="56" height="55"/>
    <SubTexture name="jump7.png" x="174" y="0" width="56" height="55"/>
    <SubTexture name="jump8.png" x="116" y="399" width="56" height="55"/>
    <SubTexture name="jump9.png" x="116" y="342" width="56" height="55"/>
    <SubTexture name="jump_shoot1.png" x="232" y="114" width="56" height="55"/>
    <SubTexture name="jump_shoot2.png" x="232" y="57" width="56" height="55"/>
    <SubTexture name="jump_shoot3.png" x="232" y="0" width="56" height="55"/>
    <SubTexture name="jump_shoot4.png" x="174" y="399" width="56" height="55"/>
    <SubTexture name="jump_shoot5.png" x="174" y="342" width="56" height="55"/>
    <SubTexture name="run1.png" x="58" y="171" width="56" height="55"/>
    <SubTexture name="run2.png" x="58" y="114" width="56" height="55"/>
    <SubTexture name="run3.png" x="58" y="57" width="56" height="55"/>
    <SubTexture name="run4.png" x="58" y="0" width="56" height="55"/>
    <SubTexture name="run5.png" x="0" y="399" width="56" height="55"/>
    <SubTexture name="run6.png" x="0" y="342" width="56" height="55"/>
    <SubTexture name="run7.png" x="0" y="285" width="56" height="55"/>
    <SubTexture name="run8.png" x="0" y="228" width="56" height="55"/>
    <SubTexture name="run_shoot1.png" x="116" y="228" width="56" height="55"/>
    <SubTexture name="run_shoot2.png" x="116" y="171" width="56" height="55"/>
    <SubTexture name="run_shoot3.png" x="116" y="114" width="56" height="55"/>
    <SubTexture name="run_shoot4.png" x="116" y="57" width="56" height="55"/>
    <SubTexture name="run_shoot5.png" x="116" y="0" width="56" height="55"/>
    <SubTexture name="run_shoot6.png" x="58" y="399" width="56" height="55"/>
    <SubTexture name="run_shoot7.png" x="58" y="342" width="56" height="55"/>
    <SubTexture name="run_shoot8.png" x="58" y="285" width="56" height="55"/>
    <SubTexture name="run_shoot9.png" x="58" y="228" width="56" height="55"/>
    <SubTexture name="shoot1.png" x="0" y="171" width="56" height="55"/>
    <SubTexture name="shoot2.png" x="0" y="114" width="56" height="55"/>
    <SubTexture name="shoot3.png" x="0" y="57" width="56" height="55"/>
    <SubTexture name="shoot4.png" x="0" y="0" width="56" height="55"/>
</TextureAtlas>